autota/__init__.py
autota/generator.py
autota/grader.py
autota/model.py
autota/recommender.py
autota/util.py
autota-0.0.3.dist-info/LICENSE
autota-0.0.3.dist-info/METADATA
autota-0.0.3.dist-info/WHEEL
autota-0.0.3.dist-info/top_level.txt
autota-0.0.3.dist-info/RECORD
