Metadata-Version: 2.1
Name: autota
Version: 0.0.3
Summary: Automatic generate QA from slides and grade marker/memo.
Home-page: https://github.com/miyuiki/autota
Author: Jay
Author-email: a121406@gmail.com
License: UNKNOWN
Platform: UNKNOWN
Classifier: Development Status :: 1 - Planning
Classifier: Programming Language :: Python :: 3
Classifier: License :: OSI Approved :: MIT License
Classifier: Operating System :: OS Independent
Requires-Python: >=3.6
